<?xml version="1.0"?>
<Root>
	<monitor index="0">
		<vertex>
			<coord>-0.150000006</coord>
			<coord>-0.300000012</coord>
		</vertex>
		<vertex>
			<coord>0.150000006</coord>
			<coord>-0.300000012</coord>
		</vertex>
		<vertex>
			<coord>0.150000006</coord>
			<coord>0.300000012</coord>
		</vertex>
		<vertex>
			<coord>-0.150000006</coord>
			<coord>0.300000012</coord>
		</vertex>
	</monitor>
	<monitor index="1">
		<vertex>
			<coord>-0.150000006</coord>
			<coord>-0.300000012</coord>
		</vertex>
		<vertex>
			<coord>0.150000006</coord>
			<coord>-0.300000012</coord>
		</vertex>
		<vertex>
			<coord>0.150000006</coord>
			<coord>0.300000012</coord>
		</vertex>
		<vertex>
			<coord>-0.150000006</coord>
			<coord>0.300000012</coord>
		</vertex>
	</monitor>
	<monitor index="2">
		<vertex>
			<coord>-0.150000006</coord>
			<coord>-0.300000012</coord>
		</vertex>
		<vertex>
			<coord>0.150000006</coord>
			<coord>-0.300000012</coord>
		</vertex>
		<vertex>
			<coord>0.150000006</coord>
			<coord>0.300000012</coord>
		</vertex>
		<vertex>
			<coord>-0.150000006</coord>
			<coord>0.300000012</coord>
		</vertex>
	</monitor>
	<monitor index="3">
		<vertex>
			<coord>-0.150000006</coord>
			<coord>-0.300000012</coord>
		</vertex>
		<vertex>
			<coord>0.150000006</coord>
			<coord>-0.300000012</coord>
		</vertex>
		<vertex>
			<coord>0.150000006</coord>
			<coord>0.300000012</coord>
		</vertex>
		<vertex>
			<coord>-0.150000006</coord>
			<coord>0.300000012</coord>
		</vertex>
	</monitor>
	<monitor index="4">
		<vertex>
			<coord>-0.150000006</coord>
			<coord>-0.300000012</coord>
		</vertex>
		<vertex>
			<coord>0.150000006</coord>
			<coord>-0.300000012</coord>
		</vertex>
		<vertex>
			<coord>0.150000006</coord>
			<coord>0.300000012</coord>
		</vertex>
		<vertex>
			<coord>-0.150000006</coord>
			<coord>0.300000012</coord>
		</vertex>
	</monitor>
	<monitor index="5">
		<vertex>
			<coord>-0.150000006</coord>
			<coord>-0.300000012</coord>
		</vertex>
		<vertex>
			<coord>0.150000006</coord>
			<coord>-0.300000012</coord>
		</vertex>
		<vertex>
			<coord>0.150000006</coord>
			<coord>0.300000012</coord>
		</vertex>
		<vertex>
			<coord>-0.150000006</coord>
			<coord>0.300000012</coord>
		</vertex>
	</monitor>
</Root>
